MANIFEST.in
changes.txt
license.txt
readme.md
setup.cfg
setup.py
nive_cms/__init__.py
nive_cms/app.py
nive_cms/baseobjects.py
nive_cms/box.py
nive_cms/codeblock.py
nive_cms/column.py
nive_cms/file.py
nive_cms/i18n.py
nive_cms/image.py
nive_cms/link.py
nive_cms/media.py
nive_cms/menublock.py
nive_cms/news.py
nive_cms/note.py
nive_cms/page.py
nive_cms/root.py
nive_cms/spacer.py
nive_cms/text.py
nive_cms.egg-info/PKG-INFO
nive_cms.egg-info/SOURCES.txt
nive_cms.egg-info/dependency_links.txt
nive_cms.egg-info/entry_points.txt
nive_cms.egg-info/not-zip-safe
nive_cms.egg-info/requires.txt
nive_cms.egg-info/top_level.txt
nive_cms/cmsview/__init__.py
nive_cms/cmsview/add.pt
nive_cms/cmsview/admin.py
nive_cms/cmsview/cmsroot.py
nive_cms/cmsview/cutcopy.py
nive_cms/cmsview/delete.pt
nive_cms/cmsview/edit.pt
nive_cms/cmsview/index.pt
nive_cms/cmsview/meta.pt
nive_cms/cmsview/sort.pt
nive_cms/cmsview/sort.py
nive_cms/cmsview/view.pt
nive_cms/cmsview/view.py
nive_cms/cmsview/static/cmseditor.css
nive_cms/cmsview/static/cmseditor.js
nive_cms/cmsview/static/cmsview.css
nive_cms/cmsview/static/cmsview.js
nive_cms/cmsview/static/images/account.png
nive_cms/cmsview/static/images/copy.png
nive_cms/cmsview/static/images/create.png
nive_cms/cmsview/static/images/cut.png
nive_cms/cmsview/static/images/delete.png
nive_cms/cmsview/static/images/direction.png
nive_cms/cmsview/static/images/document-tree.png
nive_cms/cmsview/static/images/down.png
nive_cms/cmsview/static/images/dummy.png
nive_cms/cmsview/static/images/editor.png
nive_cms/cmsview/static/images/element.png
nive_cms/cmsview/static/images/element_add.png
nive_cms/cmsview/static/images/exclamation.png
nive_cms/cmsview/static/images/jumpto.png
nive_cms/cmsview/static/images/loadingAnimation.gif
nive_cms/cmsview/static/images/logocms.png
nive_cms/cmsview/static/images/logout.png
nive_cms/cmsview/static/images/nav_down.png
nive_cms/cmsview/static/images/nav_up.png
nive_cms/cmsview/static/images/nive-cms-white-20.png
nive_cms/cmsview/static/images/node.png
nive_cms/cmsview/static/images/off.png
nive_cms/cmsview/static/images/on.png
nive_cms/cmsview/static/images/parent.png
nive_cms/cmsview/static/images/paste.png
