Metadata-Version: 1.1
Name: nive-cms
Version: 1.0rc2
Summary: Nive cms - out of the box content management system for mobile and desktop websites based on the webframework pyramid
Home-page: http://os.nive.co/
Author: Arndt Droullier, Nive GmbH
Author-email: info@nive.co
License: GPL 3
Keywords: cms website publisher pyramid
Platform: UNKNOWN
Classifier: Intended Audience :: Developers
Classifier: Programming Language :: Python
Classifier: Framework :: Pyramid
Classifier: License :: OSI Approved :: GNU General Public License v3 (GPLv3)
Classifier: Development Status :: 4 - Beta
Classifier: Programming Language :: Python :: 2.6
Classifier: Programming Language :: Python :: 2.7
